ttsmaker/__init__.py
ttsmaker/ttsmaker.py
ttsmaker-0.2.dist-info/METADATA
ttsmaker-0.2.dist-info/WHEEL
ttsmaker-0.2.dist-info/top_level.txt
ttsmaker-0.2.dist-info/RECORD
