Metadata-Version: 2.1
Name: ttsmaker
Version: 0.2
Summary: A Python library for interacting with TTSMaker API
Home-page: https://github.com/williamxhero/ttsmaker
Author: Yosef
Author-email: williamxhero@gmail.com
License: UNKNOWN
Platform: UNKNOWN
Classifier: Programming Language :: Python :: 3
Classifier: License :: OSI Approved :: MIT License
Classifier: Operating System :: OS Independent
Requires-Python: >=3.11
Requires-Dist: requests
